<annotation>
	<folder>material-cuero</folder>
	<filename>cuero431.jpg</filename>
	<path>/Users/mariaagustinamarkosich/Documents/TrabajoProfesional/tp-prof-images/material-cuero/cuero431.jpg</path>
	<source>
		<database>Unknown</database>
	</source>
	<size>
		<width>474</width>
		<height>474</height>
		<depth>3</depth>
	</size>
	<segmented>0</segmented>
	<object>
		<name>cuero</name>
		<pose>Unspecified</pose>
		<truncated>1</truncated>
		<difficult>0</difficult>
		<bndbox>
			<xmin>1</xmin>
			<ymin>61</ymin>
			<xmax>474</xmax>
			<ymax>407</ymax>
		</bndbox>
	</object>
</annotation>
