<annotation>
	<folder>cueros-pinterest</folder>
	<filename>cuero-pinteret446.jpg</filename>
	<path>/Users/mariaagustinamarkosich/Documents/TrabajoProfesional/tp-prof-images/cueros-pinterest/cuero-pinteret446.jpg</path>
	<source>
		<database>Unknown</database>
	</source>
	<size>
		<width>716</width>
		<height>895</height>
		<depth>3</depth>
	</size>
	<segmented>0</segmented>
	<object>
		<name>cuero</name>
		<pose>Unspecified</pose>
		<truncated>0</truncated>
		<difficult>0</difficult>
		<bndbox>
			<xmin>275</xmin>
			<ymin>315</ymin>
			<xmax>469</xmax>
			<ymax>769</ymax>
		</bndbox>
	</object>
</annotation>
