<annotation>
	<folder>nylon-pinterest</folder>
	<filename>nylon-pinteret47.jpg</filename>
	<path>/Users/mariaagustinamarkosich/Documents/TrabajoProfesional/tp-prof-images/nylon-pinterest/nylon-pinteret47.jpg</path>
	<source>
		<database>Unknown</database>
	</source>
	<size>
		<width>645</width>
		<height>967</height>
		<depth>3</depth>
	</size>
	<segmented>0</segmented>
	<object>
		<name>nylon</name>
		<pose>Unspecified</pose>
		<truncated>0</truncated>
		<difficult>0</difficult>
		<bndbox>
			<xmin>45</xmin>
			<ymin>349</ymin>
			<xmax>458</xmax>
			<ymax>738</ymax>
		</bndbox>
	</object>
</annotation>
