<annotation>
	<folder>cartera-cuero</folder>
	<filename>cartera-cuero-270.jpg</filename>
	<path>/Users/mariaagustinamarkosich/Documents/TrabajoProfesional/tp-prof-images/cartera-cuero/cartera-cuero-270.jpg</path>
	<source>
		<database>Unknown</database>
	</source>
	<size>
		<width>426</width>
		<height>568</height>
		<depth>3</depth>
	</size>
	<segmented>0</segmented>
	<object>
		<name>cartera</name>
		<pose>Unspecified</pose>
		<truncated>0</truncated>
		<difficult>0</difficult>
		<bndbox>
			<xmin>78</xmin>
			<ymin>250</ymin>
			<xmax>366</xmax>
			<ymax>550</ymax>
		</bndbox>
	</object>
</annotation>
