<annotation>
	<folder>cueros-pinterest</folder>
	<filename>cuero-pinteret629.jpg</filename>
	<path>/Users/mariaagustinamarkosich/Documents/TrabajoProfesional/tp-prof-images/cueros-pinterest/cuero-pinteret629.jpg</path>
	<source>
		<database>Unknown</database>
	</source>
	<size>
		<width>308</width>
		<height>422</height>
		<depth>3</depth>
	</size>
	<segmented>0</segmented>
	<object>
		<name>cuero</name>
		<pose>Unspecified</pose>
		<truncated>1</truncated>
		<difficult>0</difficult>
		<bndbox>
			<xmin>1</xmin>
			<ymin>180</ymin>
			<xmax>94</xmax>
			<ymax>415</ymax>
		</bndbox>
	</object>
</annotation>
